[
  {
    "product": {
      "name": "Sleepy Ian",
      "description": "Graphic artwork of Ian sleeping",
      "price": "100.00",
      "category_id": "categories[0].id"
    }
  },
  {
    "product": {
      "name": "Daffodil Line Drawing",
      "description": "Line drawing of daffodils",
      "price": "40.00",
      "category_id": "categories[0].id"
    }
  },
  {
    "product": {
      "name": "Hang Loose",
      "description": "Hang loose hand line drawing",
      "price": "40.00",
      "category_id": "categories[0].id"
    }
  },
  {
    "product": {
      "name": "Self Portrait Line Drawing",
      "description": "Line drawing of myself",
      "price": "40.00",
      "category_id": "categories[0].id"
    }
  }
]
